cli.py
ml_cli-0.2.1.dist-info/METADATA
ml_cli-0.2.1.dist-info/WHEEL
ml_cli-0.2.1.dist-info/entry_points.txt
ml_cli-0.2.1.dist-info/top_level.txt
ml_cli-0.2.1.dist-info/RECORD
